Metadata-Version: 1.1
Name: questionnaire
Version: 0.4.2
Summary: Uses https://github.com/wong2/pick to prompt user to fill out a questionnaire, and returns the results as a dict
Home-page: https://github.com/kylebebak/questionnaire
Author: kylebebak
Author-email: kylebebak@gmail.com
License: MIT
Download-URL: https://github.com/kylebebak/questionnaire/tarball/0.4.2
Keywords: terminal gui pick
Platform: UNKNOWN
Classifier: Intended Audience :: Developers
Classifier: License :: OSI Approved :: MIT License
Classifier: Programming Language :: Python
